Metadata-Version: 2.1
Name: drf-filtermapbackend
Version: 0.0.1
Summary: FilterBackend which takes mapping of query params to field name.
Home-page: https://github.com/aayulogic/filtermapbackend/
Author: Aayulogic Pvt. Ltd.
Author-email: info@aayulogic.com
License: GNU GENERAL PUBLIC LICENSE
Project-URL: Bug Tracker, https://github.com/aayulogic/filtermapbackend/issues
Platform: UNKNOWN
Classifier: Programming Language :: Python :: 3
Classifier: Development Status :: 3 - Alpha
Classifier: Intended Audience :: Developers
Classifier: Operating System :: OS Independent
Requires-Python: >=3.6
